setup.cfg
setup.py
botornot/__init__.py
botornot.egg-info/PKG-INFO
botornot.egg-info/SOURCES.txt
botornot.egg-info/dependency_links.txt
botornot.egg-info/requires.txt
botornot.egg-info/top_level.txt