Metadata-Version: 1.1
Name: botornot
Version: 0.3
Summary: Check Twitter accounts for bot behavior
Home-page: https://github.com/truthy/botornot-python
Author: Clayton A Davis
Author-email: claydavi@indiana.edu
License: MIT
Download-URL: https://github.com/truthy/botornot-python/archive/0.3.zip
Platform: UNKNOWN
